{"version":2,"kind":"Article","sha256":"deee738a82259f0e525dc70c9b74361f46307cdc4e5c4b1a50ffcb4ba98950f0","slug":"staff","location":"/staff.md","dependencies":[],"frontmatter":{"title":"Course Staff","downloads":[],"thumbnail":"/cse150a250a-fa25/build/trevor-8019bb966a446e2e6623cc41b418ec58.png","exports":[{"format":"md","filename":"staff.md","url":"/cse150a250a-fa25/build/staff-8abb45f5bdb94c804c716532ce906df1.md"}]},"mdast":{"type":"root","children":[{"type":"block","children":[{"type":"heading","depth":2,"position":{"start":{"line":7,"column":1},"end":{"line":7,"column":1}},"children":[{"type":"text","value":"Instructor","position":{"start":{"line":7,"column":1},"end":{"line":7,"column":1}},"key":"kVxsUcGKQH"}],"identifier":"instructor","label":"Instructor","html_id":"instructor","implicit":true,"key":"Ak6oDzKKPZ"},{"type":"grid","columns":[1,1,2,2],"children":[{"type":"card","children":[{"type":"header","children":[{"type":"paragraph","children":[{"type":"link","url":"https://tbonjour.github.io/","position":{"start":{"line":10,"column":1},"end":{"line":10,"column":1}},"children":[{"type":"text","value":"Trevor Bonjour","position":{"start":{"line":10,"column":1},"end":{"line":10,"column":1}},"key":"vsrquytlim"}],"urlSource":"https://tbonjour.github.io/","key":"lFBaneBwM0"},{"type":"text","value":" (He/Him)","position":{"start":{"line":10,"column":1},"end":{"line":10,"column":1}},"key":"NafB1dhvPJ"}],"key":"fCtorLrxI7"}],"key":"jxnwdNUvHI"},{"type":"image","url":"/cse150a250a-fa25/build/trevor-8019bb966a446e2e6623cc41b418ec58.png","alt":"Headshot of Trevor Bonjour","width":"128px","align":"center","class":"staff-headshot","key":"mrL0Qu7xQi","urlSource":"staff-images/trevor.png"},{"type":"comment","value":" Short description here: who you are, what do you like doing when not working, etc.  ","key":"ci6pOmlDhN"},{"type":"footer","children":[{"type":"paragraph","children":[{"type":"link","url":"mailto:tbonjour@ucsd.edu","position":{"start":{"line":11,"column":1},"end":{"line":11,"column":1}},"children":[{"type":"text","value":"tbonjour@ucsd.edu","position":{"start":{"line":11,"column":1},"end":{"line":11,"column":1}},"key":"OSfnGcv2no"}],"urlSource":"mailto:tbonjour@ucsd.edu","key":"EFBoDBCubq"},{"type":"text","value":", Office: CSE 2114","position":{"start":{"line":11,"column":1},"end":{"line":11,"column":1}},"key":"wB8XxP8tSE"}],"key":"JAu4l0o03l"}],"key":"RRBppbVkOm"}],"key":"DTrhEzCv0j"}],"key":"uAAKBayP3O"},{"type":"heading","depth":2,"position":{"start":{"line":22,"column":1},"end":{"line":22,"column":1}},"children":[{"type":"text","value":"Teaching Assistants","position":{"start":{"line":22,"column":1},"end":{"line":22,"column":1}},"key":"LpCZ5wBMYs"}],"identifier":"teaching-assistants","label":"Teaching Assistants","html_id":"teaching-assistants","implicit":true,"key":"HNuvgd8hqM"},{"type":"grid","columns":[1,1,2,2],"children":[{"type":"card","children":[{"type":"header","children":[{"type":"paragraph","children":[{"type":"text","value":"Ayush Parasbhai Maniar","position":{"start":{"line":25,"column":1},"end":{"line":25,"column":1}},"key":"sGxMqe2mZr"}],"key":"ryp4uKcxGe"}],"key":"cYy5PqKaLp"},{"type":"image","url":"/cse150a250a-fa25/build/Ayush-b2fc5c8205ec24ff59e60c847c2ad0b0.jpeg","alt":"Headshot of Ayush Parasbhai Maniar","align":"center","class":"staff-headshot","key":"AhH74I09Wd","urlSource":"staff-images/Ayush.jpeg"},{"type":"comment","value":" Short description here: who you are, what do you like doing when not working, etc.  ","key":"HSlGbfxtne"},{"type":"footer","children":[{"type":"paragraph","children":[{"type":"link","url":"mailto:aymaniar@ucsd.edu","position":{"start":{"line":26,"column":1},"end":{"line":26,"column":1}},"children":[{"type":"text","value":"aymaniar@ucsd.edu","position":{"start":{"line":26,"column":1},"end":{"line":26,"column":1}},"key":"wB1csIBSmW"}],"urlSource":"mailto:aymaniar@ucsd.edu","key":"L4QRNaF7pb"}],"key":"f6uLCfZoA5"}],"key":"mIKegxQTN2"}],"key":"XdBPwlljvt"},{"type":"card","children":[{"type":"header","children":[{"type":"paragraph","children":[{"type":"text","value":"Eric Jialong Song","position":{"start":{"line":35,"column":1},"end":{"line":35,"column":1}},"key":"wlq6I9KQEg"}],"key":"yVgHGuAP8s"}],"key":"h7hIVFceTk"},{"type":"image","url":"/cse150a250a-fa25/build/Eric2-5b9afa0ae43d914b010f9493ff84b431.jpg","alt":"Headshot of Eric Jialong Song","align":"center","class":"staff-headshot","key":"XtexOaFQq0","urlSource":"staff-images/Eric2.jpg"},{"type":"comment","value":" Short description here: who you are, what do you like doing when not working, etc.  ","key":"uKe3P2zSmx"},{"type":"footer","children":[{"type":"paragraph","children":[{"type":"link","url":"mailto:ejsong@ucsd.edu","position":{"start":{"line":36,"column":1},"end":{"line":36,"column":1}},"children":[{"type":"text","value":"ejsong@ucsd.edu","position":{"start":{"line":36,"column":1},"end":{"line":36,"column":1}},"key":"on5J6dqa6P"}],"urlSource":"mailto:ejsong@ucsd.edu","key":"DQQ3kZJyrS"}],"key":"SA5YnabqmW"}],"key":"sW1EEsALyv"}],"key":"Bz0Z9tP95d"},{"type":"card","children":[{"type":"header","children":[{"type":"paragraph","children":[{"type":"text","value":"Francis Geng","position":{"start":{"line":45,"column":1},"end":{"line":45,"column":1}},"key":"VpJWtxMiA4"}],"key":"FNrJYbexb7"}],"key":"YFflpeqklB"},{"type":"image","url":"/cse150a250a-fa25/build/francis-da974cf76f8bb0c13fb998678d92c55d.JPG","alt":"Headshot of Francis Geng","align":"center","class":"staff-headshot","key":"fHPuIcbQF4","urlSource":"staff-images/francis.JPG"},{"type":"comment","value":" Short description here: who you are, what do you like doing when not working, etc.  ","key":"F1sGOsEKNl"},{"type":"footer","children":[{"type":"paragraph","children":[{"type":"link","url":"mailto:fgeng@ucsd.edu","position":{"start":{"line":46,"column":1},"end":{"line":46,"column":1}},"children":[{"type":"text","value":"fgeng@ucsd.edu","position":{"start":{"line":46,"column":1},"end":{"line":46,"column":1}},"key":"pL8ZBVxxrg"}],"urlSource":"mailto:fgeng@ucsd.edu","key":"vASAuQGFrj"}],"key":"gjCTTVxeRp"}],"key":"OXDV0wE5MJ"}],"key":"OwX2BwaQcg"},{"type":"card","children":[{"type":"header","children":[{"type":"paragraph","children":[{"type":"text","value":"Harsh Harshvardhan","position":{"start":{"line":55,"column":1},"end":{"line":55,"column":1}},"key":"edcSl2TLa3"}],"key":"qNRmMwqZ5R"}],"key":"CFOg9Iz8iX"},{"type":"image","url":"/cse150a250a-fa25/build/Harshvardhan-b7336afa171fa11b9a8186c9649aa417.png","alt":"Headshot of Harsh Harshvardhan","align":"center","class":"staff-headshot","key":"byU94LnuYL","urlSource":"staff-images/Harshvardhan.png"},{"type":"comment","value":" Short description here: who you are, what do you like doing when not working, etc.  ","key":"lq6qpZyBkF"},{"type":"footer","children":[{"type":"paragraph","children":[{"type":"link","url":"mailto:hharshvardhan@ucsd.edu","position":{"start":{"line":56,"column":1},"end":{"line":56,"column":1}},"children":[{"type":"text","value":"hharshvardhan@ucsd​.edu","position":{"start":{"line":56,"column":1},"end":{"line":56,"column":1}},"key":"rLHCcO6qwo"}],"urlSource":"mailto:hharshvardhan@ucsd.edu","key":"aCsFgMhyMV"}],"key":"i99qt6nDfB"}],"key":"wBDjPfKelz"}],"key":"LEPKSYk3vJ"},{"type":"card","children":[{"type":"header","children":[{"type":"paragraph","children":[{"type":"text","value":"Ruolan Yang","position":{"start":{"line":65,"column":1},"end":{"line":65,"column":1}},"key":"GbX4Zh6F4q"}],"key":"f0wnbfFGMh"}],"key":"kYnEzSC5ZH"},{"type":"image","url":"/cse150a250a-fa25/build/ruolan-4151595409e9d9962df3c99d1e7c9768.jpg","alt":"Headshot of Ruolan Yang","align":"center","class":"staff-headshot","key":"QLiiElPYOp","urlSource":"staff-images/ruolan.jpg"},{"type":"comment","value":" Short description here: who you are, what do you like doing when not working, etc.  ","key":"XrJri6RQhD"},{"type":"footer","children":[{"type":"paragraph","children":[{"type":"link","url":"mailto:ruy009@ucsd.edu","position":{"start":{"line":66,"column":1},"end":{"line":66,"column":1}},"children":[{"type":"text","value":"ruy009@ucsd.edu","position":{"start":{"line":66,"column":1},"end":{"line":66,"column":1}},"key":"DT5QZBEmL0"}],"urlSource":"mailto:ruy009@ucsd.edu","key":"fu9HKC8Rf0"}],"key":"vomKxzuOwa"}],"key":"vVQANGbtUR"}],"key":"beVgGQZRud"},{"type":"card","children":[{"type":"header","children":[{"type":"paragraph","children":[{"type":"text","value":"Sharanya Milind Ranka","position":{"start":{"line":75,"column":1},"end":{"line":75,"column":1}},"key":"fjUaNdwFOj"}],"key":"PIJKH7FkFU"}],"key":"keWEySrC8B"},{"type":"image","url":"/cse150a250a-fa25/build/sharanya-2ad6713db1c08a154b87e26332d8406e.jpg","alt":"Headshot of Sharanya Milind Ranka","align":"center","class":"staff-headshot","key":"YSr6YMmp1f","urlSource":"staff-images/sharanya.jpg"},{"type":"comment","value":" Short description here: who you are, what do you like doing when not working, etc.  ","key":"rq7Ym2YbZ7"},{"type":"footer","children":[{"type":"paragraph","children":[{"type":"link","url":"mailto:smranka@ucsd.edu","position":{"start":{"line":76,"column":1},"end":{"line":76,"column":1}},"children":[{"type":"text","value":"smranka@ucsd.edu","position":{"start":{"line":76,"column":1},"end":{"line":76,"column":1}},"key":"ilnVy2KQEg"}],"urlSource":"mailto:smranka@ucsd.edu","key":"PlVEW7dNie"}],"key":"nbS4FTbuEL"}],"key":"jXO2VZz9ll"}],"key":"LFWDfNsR3j"},{"type":"card","children":[{"type":"header","children":[{"type":"paragraph","children":[{"type":"text","value":"Sohyun Yoo","position":{"start":{"line":85,"column":1},"end":{"line":85,"column":1}},"key":"ABkPwi9hNZ"}],"key":"uI3sbbrtmX"}],"key":"PWqeiRCeTW"},{"type":"image","url":"/cse150a250a-fa25/build/sohyun-ff0ef2f00030a1ef31278df8ad15df83.jpg","alt":"Headshot of Sohyun Yoo","align":"center","class":"staff-headshot","key":"XbZcy80eJl","urlSource":"staff-images/sohyun.jpg"},{"type":"comment","value":" Short description here: who you are, what do you like doing when not working, etc.  ","key":"t9XiVtdYHC"},{"type":"footer","children":[{"type":"paragraph","children":[{"type":"link","url":"mailto:soyoo@ucsd.edu","position":{"start":{"line":86,"column":1},"end":{"line":86,"column":1}},"children":[{"type":"text","value":"soyoo@ucsd.edu","position":{"start":{"line":86,"column":1},"end":{"line":86,"column":1}},"key":"k2WyxPtNJn"}],"urlSource":"mailto:soyoo@ucsd.edu","key":"H7mL9w8Ckq"}],"key":"vKFXHTDf3B"}],"key":"Vz8efgmATC"}],"key":"uqS9ViFvKA"},{"type":"card","children":[{"type":"header","children":[{"type":"paragraph","children":[{"type":"text","value":"Tianyi Zheng","position":{"start":{"line":95,"column":1},"end":{"line":95,"column":1}},"key":"ZIrawqHEjE"}],"key":"s2yVOVUiIv"}],"key":"etybcZi9bm"},{"type":"image","url":"/cse150a250a-fa25/build/tianyi-c525fa1ff54ece2a82daa6e2034717ed.jpg","alt":"Headshot of Tianyi Zheng","align":"center","class":"staff-headshot","key":"wMgHiK4d84","urlSource":"staff-images/tianyi.jpg"},{"type":"comment","value":" Short description here: who you are, what do you like doing when not working, etc.  ","key":"nKjweSMgEQ"},{"type":"footer","children":[{"type":"paragraph","children":[{"type":"link","url":"mailto:t4zheng@ucsd.edu","position":{"start":{"line":96,"column":1},"end":{"line":96,"column":1}},"children":[{"type":"text","value":"t4zheng@ucsd.edu","position":{"start":{"line":96,"column":1},"end":{"line":96,"column":1}},"key":"TQAovp1ZXB"}],"urlSource":"mailto:t4zheng@ucsd.edu","key":"o9aM2r20OQ"}],"key":"G5gnGrP6NK"}],"key":"qtsRVMMIpQ"}],"key":"yJuE5Pk9w6"},{"type":"card","children":[{"type":"header","children":[{"type":"paragraph","children":[{"type":"text","value":"Tianyu Chen","position":{"start":{"line":105,"column":1},"end":{"line":105,"column":1}},"key":"BLCH1VXi83"}],"key":"J6BVLLU5S1"}],"key":"kvnQiJ4mOo"},{"type":"image","url":"/cse150a250a-fa25/build/tianyu-4920b39c6120ff2e99e3d3cb8d40e5b7.png","alt":"Headshot of Tianyu Chen","align":"center","class":"staff-headshot","key":"hi9j8BEG4f","urlSource":"staff-images/tianyu.png"},{"type":"comment","value":" Short description here: who you are, what do you like doing when not working, etc.  ","key":"UCZ6gZa4gs"},{"type":"footer","children":[{"type":"paragraph","children":[{"type":"link","url":"mailto:tic004@ucsd.edu","position":{"start":{"line":106,"column":1},"end":{"line":106,"column":1}},"children":[{"type":"text","value":"tic004@ucsd.edu","position":{"start":{"line":106,"column":1},"end":{"line":106,"column":1}},"key":"qq1zJSp5pl"}],"urlSource":"mailto:tic004@ucsd.edu","key":"bRcnuUYtKl"}],"key":"f3kCRHDgWe"}],"key":"XnFeDdBpTq"}],"key":"v2K7Mugnt3"}],"key":"h19ouB2e3w"},{"type":"heading","depth":2,"position":{"start":{"line":116,"column":1},"end":{"line":116,"column":1}},"children":[{"type":"text","value":"Tutors","position":{"start":{"line":116,"column":1},"end":{"line":116,"column":1}},"key":"GwXrqvUl6h"}],"identifier":"tutors","label":"Tutors","html_id":"tutors","implicit":true,"key":"ljllJL7Ajn"},{"type":"grid","columns":[1,1,2,2],"children":[{"type":"card","children":[{"type":"header","children":[{"type":"paragraph","children":[{"type":"text","value":"Phillip Long","position":{"start":{"line":120,"column":1},"end":{"line":120,"column":1}},"key":"uzGW65A8AF"}],"key":"kjoxjNIv4Z"}],"key":"hlXMcCmBqF"},{"type":"image","url":"/cse150a250a-fa25/build/phillip-0eed4e405fbf248418ceaf572cbe4876.png","alt":"Headshot of Phillip Long","align":"center","class":"staff-headshot","key":"NjaxL2aPBR","urlSource":"staff-images/phillip.png"},{"type":"comment","value":" Short description here: who you are, what do you like doing when not working, etc.  ","key":"TzwnO7IbX5"},{"type":"footer","children":[{"type":"paragraph","children":[{"type":"link","url":"mailto:p1long@ucsd.edu","position":{"start":{"line":121,"column":1},"end":{"line":121,"column":1}},"children":[{"type":"text","value":"p1long@ucsd.edu","position":{"start":{"line":121,"column":1},"end":{"line":121,"column":1}},"key":"TEelf5R781"}],"urlSource":"mailto:p1long@ucsd.edu","key":"I0N2eipg12"}],"key":"URSHXW0psq"}],"key":"ddHZH1SzDu"}],"key":"sOkzwDDcrp"},{"type":"card","children":[{"type":"header","children":[{"type":"paragraph","children":[{"type":"text","value":"Sarah Athena Chun","position":{"start":{"line":130,"column":1},"end":{"line":130,"column":1}},"key":"Rsikwdd32o"}],"key":"pSZWubp3R9"}],"key":"TdNdXEblzE"},{"type":"image","url":"/cse150a250a-fa25/build/sarah-d9bf3e020e1d9c55a72db693bb551ad9.jpg","alt":"Headshot of Sarah Athena Chun","align":"center","class":"staff-headshot","key":"oY6xbPDo8g","urlSource":"staff-images/sarah.jpg"},{"type":"comment","value":" Short description here: who you are, what do you like doing when not working, etc.  ","key":"Z1ywzCGzUx"},{"type":"footer","children":[{"type":"paragraph","children":[{"type":"link","url":"mailto:s7chun@ucsd.edu","position":{"start":{"line":131,"column":1},"end":{"line":131,"column":1}},"children":[{"type":"text","value":"s7chun@ucsd.edu","position":{"start":{"line":131,"column":1},"end":{"line":131,"column":1}},"key":"CbjsW61VJj"}],"urlSource":"mailto:s7chun@ucsd.edu","key":"UNZqAOmXMj"}],"key":"jBs7gNKTkU"}],"key":"nvewrSUGX7"}],"key":"qj3037mkXp"},{"type":"card","children":[{"type":"header","children":[{"type":"paragraph","children":[{"type":"text","value":"Satvi Kammula","position":{"start":{"line":140,"column":1},"end":{"line":140,"column":1}},"key":"hfF7rjDiBJ"}],"key":"s0dpKvSkRS"}],"key":"v5DZnIdfz7"},{"type":"image","url":"/cse150a250a-fa25/build/Satvi-17f790a3665f3d662030368033ae56e3.jpeg","alt":"Headshot of Satvi Kammula","align":"center","class":"staff-headshot","key":"Cg4gB27723","urlSource":"staff-images/Satvi.jpeg"},{"type":"comment","value":" Short description here: who you are, what do you like doing when not working, etc.  ","key":"GSGzBWU9Nr"},{"type":"footer","children":[{"type":"paragraph","children":[{"type":"link","url":"mailto:sakammula@ucsd.edu","position":{"start":{"line":141,"column":1},"end":{"line":141,"column":1}},"children":[{"type":"text","value":"sakammula@ucsd.edu","position":{"start":{"line":141,"column":1},"end":{"line":141,"column":1}},"key":"cBoQ69mEOR"}],"urlSource":"mailto:sakammula@ucsd.edu","key":"cKGuLBAmsM"}],"key":"zn3brBUCFM"}],"key":"GWkeaxz5NT"}],"key":"V095SiaNCB"}],"key":"aJX5rHvyUk"}],"key":"I1R2XTsvSI"}],"key":"pW8h2QNZcx"},"references":{"cite":{"order":[],"data":{}}},"footer":{"navigation":{"prev":{"title":"Office Hours","url":"/office-hours","group":"CSE150A / CSE250A"}}},"domain":"http://localhost:3000"}